depchecker/__init__.py
depchecker/__main__.py
depchecker/packages.py
depchecker-0.1.dist-info/DESCRIPTION.rst
depchecker-0.1.dist-info/LICENSE.txt
depchecker-0.1.dist-info/METADATA
depchecker-0.1.dist-info/RECORD
depchecker-0.1.dist-info/WHEEL
depchecker-0.1.dist-info/metadata.json
depchecker-0.1.dist-info/top_level.txt
