Metadata-Version: 2.0
Name: depchecker
Version: 0.1
Summary: A tool that checks python project dependencies
Home-page: https://github.com/swarmer/depchecker
Author: swarmer
Author-email: anton@swarmer.me
License: MIT
Keywords: dependency,package,vulnerability,requirements
Platform: UNKNOWN
Classifier: Development Status :: 4 - Beta
Classifier: Environment :: Console
Classifier: Intended Audience :: Developers
Classifier: License :: OSI Approved :: MIT License
Classifier: Natural Language :: English
Classifier: Operating System :: OS Independent
Classifier: Programming Language :: Python :: 2
Classifier: Programming Language :: Python :: 3
Classifier: Programming Language :: Python :: Implementation :: CPython
Classifier: Programming Language :: Python :: Implementation :: PyPy
Classifier: Programming Language :: Python
Classifier: Topic :: Software Development
Requires-Dist: click (<7.0,>=6.0)
Requires-Dist: requests (<3.0,>=2.7)
Requires-Dist: setuptools (>=19.0)
Requires-Dist: six (<2.0,>=1.10)
